{"cameraMode":{"drawMode":0,"name":"Shaded","section":"Shading Mode"},"sceneLighting":true,"audioPlay":false,"sceneViewState":{"m_AlwaysRefresh":false,"showFog":true,"showSkybox":true,"showFlares":true,"showImageEffects":true,"showParticleSystems":true,"showVisualEffectGraphs":true,"m_FxEnabled":true},"in2DMode":false,"pivot":{"x":15.705580711364746,"y":2.8811423778533937,"z":0.267454594373703},"rotation":{"x":0.3408098518848419,"y":-0.052152369171381,"z":0.01897268556058407,"w":0.9385762810707092},"size":22.067264556884767,"orthographic":false}